MANIFEST.in
README.rst
setup.py
tgext.odt.egg-info/PKG-INFO
tgext.odt.egg-info/SOURCES.txt
tgext.odt.egg-info/dependency_links.txt
tgext.odt.egg-info/entry_points.txt
tgext.odt.egg-info/not-zip-safe
tgext.odt.egg-info/requires.txt
tgext.odt.egg-info/top_level.txt
tgextodt/__init__.py
tgextodt/bootstrap.py
tgextodt/model/__init__.py