Metadata-Version: 1.0
Name: tgext.odt
Version: 0.3
Summary: tgext.odt is a Pluggable application for TurboGears2 that allows the rendering of .odt (openoffice/libreoffice) documents as an output templates.
Home-page: https://github.com/puria/tgext.odt
Author: Puria Nafisi Azizi
Author-email: puria.nafisi@axant.it
License: UNKNOWN
Keywords: turbogears2.extension
Platform: UNKNOWN
